{
  "generatedAt": "2026-07-08T21:56:09.661Z",
  "kstDate": "2026-07-09",
  "kstYesterday": "2026-07-08",
  "prevWeekMon": "2026-06-29",
  "prevWeekSun": "2026-07-05",
  "daily": {
    "대항해시대 오리진": {
      "summary": "[주요 이슈]\n가장 많이 언급된 문제는 새로 개편된 \"연구\" 시스템, 특히 \"교역 연구\"의 복잡성과 과도한 비용(슬롯, 레잼)에 대한 불만입니다. 또한, 잦은 \"점검\" 연장과 미흡한 운영으로 인한 유저들의 피로감과 불만이 매우 높게 나타나고 있습니다.\n\n[유저 반응]\n전반적인 유저 반응은 매우 부정적입니다. 개악된 연구 시스템과 노골적인 과금 유도 정책에 대한 비판이 주를 이루며, 잦은 점검과 미흡한 이벤트 운영에 대한 불만으로 인해 서비스 종료를 언급하는 목소리까지 나오고 있습니다.\n\n[주목할 키워드]\n*   **연구**: 새롭게 개편된 교역 연구 시스템의 복잡성과 과도한 비용(슬롯, 레잼)에 대한 불만이 폭발적입니다.\n*   **점검**: 잦은 긴급 점검과 연장, 그리고 그에 따른 불편함에 대한 유저들의 불만이 높습니다.\n*   **과금**: 스텝업 상품 가격 인상 및 노골적인 과금 유도 정책에 대한 비판이 거세게 제기되고 있습니다.\n\n[한줄 요약]\n개악된 연구 시스템과 과도한 과금 유도, 잦은 점검으로 인해 유저들의 불만이 극에 달하며 서비스 종료까지 거론되는 매우 부정적인 분위기입니다.",
      "postCount": 72,
      "totalViews": 370,
      "totalComments": 10
    },
    "언디셈버": {
      "summary": "[주요 이슈]\n\"출혈\" (Bleed) 빌드가 커뮤니티 내에서 가장 큰 화제로 떠올랐으며, 유저들 사이에서 긍정적인 반응을 얻고 있습니다. 한편, 게임 내 \"버그\" 수정에 대한 유저의 불만도 명확히 제기되었습니다.\n\n[유저 반응]\n전반적으로 \"출혈\" 빌드의 성능에 대한 긍정적인 반응과 함께 이번 시즌에 대한 호평이 주를 이룹니다. 그러나 \"버그\" 수정이 우선되어야 한다는 명확한 부정적 의견도 나타나 복합적인 분위기입니다.\n\n[주목할 키워드]\n가장 주목할 키워드는 '출혈'로, 새로운 빌드의 성능에 대한 긍정적인 평가와 함께 유저들의 큰 관심을 받고 있습니다. '버그'는 게임 개선을 위한 필수적인 수정 사항으로 언급되며 부정적인 맥락을 가집니다.\n\n[한줄 요약]\n\"출혈\" 빌드의 흥행으로 시즌 전반에 대한 긍정적 분위기가 형성되었으나, \"버그\" 수정 요구 또한 간과할 수 없는 주요 이슈로 부상했습니다.",
      "postCount": 8,
      "totalViews": 36,
      "totalComments": 1
    },
    "창세기전 모바일": {
      "summary": "[주요 이슈]\n최근 업데이트와 콜라보 이벤트에 대한 관심이 높으며, 특히 신규 콘텐츠인 '방주'의 난이도와 관련된 질문 및 오류 보고가 많습니다. 또한 '철가면', '흑태자' 등 주요 캐릭터에 대한 논의와 함께 뽑기(가챠) 시스템에 대한 불만도 꾸준히",
      "postCount": 65,
      "totalViews": 640,
      "totalComments": 6
    }
  },
  "weekly": {
    "대항해시대 오리진": {
      "summary": "[주요 이슈]\n가장 많이 언급된 문제나 화제는 서버 통합 논의, 특히 '태1' 서버의 통합 여부와 그 영향입니다. 이와 함께 '육탐' 시스템의 전투력, 레벨링, 버그 등 다양한 측면과 '연구' 시스템 개편 및 너프 가능성에 대한 우려가 주요 관심사입니다.\n\n[유저 반응]\n전반적인 분위기는 중립적 의견과 함께 불만 및 개선 요구가 두드러집니다. 게임 시스템의 불합리함, 버그, 잠재적 너프에 대한 비판적 시각이 많으며, 서버 통합에 대한 기대와 우려가 공존합니다.\n\n[주목할 키워드]\n'서버 통합', '육탐', '연구'는 게임의 미래 방향성과 직결된 핵심 논의 주제로 반복 등장했습니다. 또한 '태1' 서버는 통합 논의의 중심에 있었으며, '버그', '렉', '너프', '상품' 등의 키워드는 게임의 문제점과 운영 방식에 대한 유저들의 관심을 보여줍니다.\n\n[한줄 요약]\n\"대항해시대 오리진\" 커뮤니티는 서버 통합, 육탐 및 연구 시스템 개편 등 주요 게임 변화에 대한 활발한 논의와 함께 다양한 개선 요구를 쏟아내고 있습니다.",
      "postCount": 111,
      "totalViews": 279,
      "totalComments": 7
    },
    "언디셈버": {
      "summary": "**[주요 이슈]**\n\"궤적의 지배자\" 증폭량 2000 버그가 명확히 보고되어 게임의 안정성에 대한 우려가 커지고 있습니다. 또한 \"언디 끝났다\", \"라인게임 망하나요?\"와 같은 게시글에서 게임의 미래와 이탈하는 유저들에 대한 불안감이 감지됩니다.\n\n",
      "postCount": 26,
      "totalViews": 49,
      "totalComments": 2
    },
    "창세기전 모바일": {
      "summary": "[주요 이슈]\n개발사의 소통 부재와 업데이트 지연에 대한 유저들의 불만이 가장 두드러집니다. 또한, 신규 캐릭터 '철가면' 출시에 대한 높은 기대감과 함께 과도한 과금 요소가 추가될까 우려하는 목소리가 큽니다. 게임 내 버그, 렉, 오류 등 기술",
      "postCount": 144,
      "totalViews": 1104,
      "totalComments": 11
    }
  }
}